barbican_tempest_plugin/README.rst
barbican_tempest_plugin/__init__.py
barbican_tempest_plugin/clients.py
barbican_tempest_plugin/config.py
barbican_tempest_plugin/plugin.py
barbican_tempest_plugin/services/__init__.py
barbican_tempest_plugin/services/key_manager/__init__.py
barbican_tempest_plugin/services/key_manager/json/__init__.py
barbican_tempest_plugin/services/key_manager/json/base.py
barbican_tempest_plugin/services/key_manager/json/consumer_client.py
barbican_tempest_plugin/services/key_manager/json/container_client.py
barbican_tempest_plugin/services/key_manager/json/order_client.py
barbican_tempest_plugin/services/key_manager/json/quota_client.py
barbican_tempest_plugin/services/key_manager/json/secret_client.py
barbican_tempest_plugin/services/key_manager/json/secret_metadata_client.py
barbican_tempest_plugin/services/key_manager/json/secret_stores_client.py
barbican_tempest_plugin/services/key_manager/json/transport_key_client.py
barbican_tempest_plugin/services/key_manager/v1_1/__init__.py
barbican_tempest_plugin/services/key_manager/v1_1/secret_consumer_client.py
barbican_tempest_plugin/services/key_manager/v1_1/version_client.py
barbican_tempest_plugin/tests/__init__.py
barbican_tempest_plugin/tests/base.py
barbican_tempest_plugin/tests/api/__init__.py
barbican_tempest_plugin/tests/api/base.py
barbican_tempest_plugin/tests/api/test_consumers.py
barbican_tempest_plugin/tests/api/test_containers.py
barbican_tempest_plugin/tests/api/test_cve_2022_3100.py
barbican_tempest_plugin/tests/api/test_orders.py
barbican_tempest_plugin/tests/api/test_quotas.py
barbican_tempest_plugin/tests/api/test_secret_consumers.py
barbican_tempest_plugin/tests/api/test_secret_metadata.py
barbican_tempest_plugin/tests/api/test_secrets.py
barbican_tempest_plugin/tests/rbac/__init__.py
barbican_tempest_plugin/tests/rbac/v1/__init__.py
barbican_tempest_plugin/tests/rbac/v1/base.py
barbican_tempest_plugin/tests/rbac/v1/test_containers.py
barbican_tempest_plugin-4.4.0.dist-info/AUTHORS
barbican_tempest_plugin-4.4.0.dist-info/LICENSE
barbican_tempest_plugin-4.4.0.dist-info/METADATA
barbican_tempest_plugin-4.4.0.dist-info/WHEEL
barbican_tempest_plugin-4.4.0.dist-info/entry_points.txt
barbican_tempest_plugin-4.4.0.dist-info/pbr.json
barbican_tempest_plugin-4.4.0.dist-info/top_level.txt
barbican_tempest_plugin-4.4.0.dist-info/RECORD
